epyk_bootstrap/__init__.py
epyk_bootstrap/core/BsDatePicker.py
epyk_bootstrap/core/BsDom.py
epyk_bootstrap/core/BsHtml.py
epyk_bootstrap/core/BsOptions.py
epyk_bootstrap/core/BsStyles.py
epyk_bootstrap/core/Page.py
epyk_bootstrap/core/__init__.py
epyk_bootstrap/interfaces/Comp.py
epyk_bootstrap/interfaces/CompButtons.py
epyk_bootstrap/interfaces/CompCarousel.py
epyk_bootstrap/interfaces/CompCollapse.py
epyk_bootstrap/interfaces/CompDates.py
epyk_bootstrap/interfaces/CompDropDowns.py
epyk_bootstrap/interfaces/CompInputs.py
epyk_bootstrap/interfaces/CompLists.py
epyk_bootstrap/interfaces/CompModals.py
epyk_bootstrap/interfaces/CompNavs.py
epyk_bootstrap/interfaces/CompScrolls.py
epyk_bootstrap/interfaces/__init__.py
epyk_bootstrap-1.0.0.dist-info/LICENSE
epyk_bootstrap-1.0.0.dist-info/METADATA
epyk_bootstrap-1.0.0.dist-info/WHEEL
epyk_bootstrap-1.0.0.dist-info/top_level.txt
epyk_bootstrap-1.0.0.dist-info/RECORD
