Metadata-Version: 2.1
Name: epyk-bootstrap
Version: 1.0.0
Summary: UNKNOWN
Home-page: https://github.com/epykure/epyk-bootstrap
Author: epykure
Author-email: smith.pyotr@gmail.com
License: UNKNOWN
Project-URL: Documentation, http://www.epyk.io
Project-URL: Code, https://github.com/epykure/epyk-bootstrap
Project-URL: Issue tracker, https://github.com/epykure/epyk-bootstrap/issues
Platform: UNKNOWN
Classifier: Programming Language :: Python :: 3
Classifier: Programming Language :: Python :: 2.7
Classifier: License :: OSI Approved :: GNU General Public License (GPL)
Classifier: Operating System :: OS Independent
Requires-Python: >=2.7
Requires-Dist: epyk
